nonebot_plugin_todo/__init__.py
nonebot_plugin_todo/data.py
nonebot_plugin_todo/handle.py
nonebot_plugin_todo/parser.py
nonebot_plugin_todo-0.1.5.dist-info/LICENSE
nonebot_plugin_todo-0.1.5.dist-info/WHEEL
nonebot_plugin_todo-0.1.5.dist-info/METADATA
nonebot_plugin_todo-0.1.5.dist-info/RECORD
